{
    "Bishop:": {
        "B": {
            "offsets": [],
            "spans": [
                "step_1sqr225d",
                "step_1sqr315d",
                "step_1sqr45d",
                "step_1sqr135d"
            ]
        },
        "W": {
            "offsets": [],
            "spans": [
                "step_1sqr45d",
                "step_1sqr135d",
                "step_1sqr225d",
                "step_1sqr315d"
            ]
        }
    },
    "Knight": {
        "B": {
            "offsets": [
                [
                    -1,
                    -2
                ],
                [
                    -1,
                    2
                ],
                [
                    1,
                    -2
                ],
                [
                    1,
                    2
                ],
                [
                    -2,
                    -1
                ],
                [
                    -2,
                    1
                ],
                [
                    2,
                    -1
                ],
                [
                    2,
                    1
                ]
            ],
            "spans": []
        },
        "W": {
            "offsets": [
                [
                    1,
                    2
                ],
                [
                    1,
                    -2
                ],
                [
                    -1,
                    2
                ],
                [
                    -1,
                    -2
                ],
                [
                    2,
                    1
                ],
                [
                    2,
                    -1
                ],
                [
                    -2,
                    1
                ],
                [
                    -2,
                    -1
                ]
            ],
            "spans": []
        }
    },
    "Queen": {
        "B": {
            "spans": [
                "step_1sqr180d",
                "step_1sqr225d",
                "step_1sqr270d",
                "step_1sqr315d",
                "step_1sqr0d",
                "step_1sqr90d",
                "step_1sqr45d",
                "step_1sqr135d"
            ]
        },
        "W": {
            "offsets": [],
            "spans": [
                "step_1sqr0d",
                "step_1sqr45d",
                "step_1sqr90d",
                "step_1sqr135d",
                "step_1sqr180d",
                "step_1sqr225d",
                "step_1sqr270d",
                "step_1sqr315d"
            ]
        },
        "offsets": []
    },
    "Rook": {
        "B": {
            "offsets": [],
            "spans": [
                "step_1sqr180d",
                "step_1sqr270d",
                "step_1sqr0d",
                "step_1sqr90d"
            ]
        },
        "W": {
            "offsets": [],
            "spans": [
                "step_1sqr0d",
                "step_1sqr90d",
                "step_1sqr180d",
                "step_1sqr270d"
            ]
        }
    },
    "hello": {
        "B": {
            "offsets": [],
            "spans": []
        },
        "W": {
            "offsets": [],
            "spans": []
        }
    },
    "myPiece": {
        "B": {
            "offsets": [],
            "spans": []
        },
        "W": {
            "offsets": [],
            "spans": []
        }
    },
    "merman": {
        "W": {
            "spans": [
                "step_1sqr315d",
                "step_1sqr225d"
            ],
            "offsets": [
                [
                    -1,
                    1
                ],
                [
                    0,
                    2
                ],
                [
                    0,
                    3
                ],
                [
                    1,
                    1
                ]
            ]
        },
        "B": {
            "spans": [
                "step_1sqr135d",
                "step_1sqr45d"
            ],
            "offsets": [
                [
                    1,
                    -1
                ],
                [
                    0,
                    -2
                ],
                [
                    0,
                    -3
                ],
                [
                    -1,
                    -1
                ]
            ]
        }
    }
}